tox_no_deps/__init__.py
tox_no_deps/plugin.py
tox_no_deps/version.py
tox_no_deps-0.3.0.dist-info/LICENSE
tox_no_deps-0.3.0.dist-info/METADATA
tox_no_deps-0.3.0.dist-info/WHEEL
tox_no_deps-0.3.0.dist-info/entry_points.txt
tox_no_deps-0.3.0.dist-info/top_level.txt
tox_no_deps-0.3.0.dist-info/RECORD
